{
  "@context": "https://schema.org",
  "@type": "Dataset",
  "axn": "AXN:0081.EMPIRICAL.📦💚🤙🔚⏫🌈",
  "deposit_number": 326,
  "generated_at": "2026-06-23T13:48:46Z",
  "schema_version": "1.0",
  "purpose": "Thin per-deposit INDEX into the recovered external metadata for this deposit's legacy Zenodo DOIs. The actual records live in the bulk data stores under data/ (openalex-severed-recovery.json, zenodo-xml-pretermination-2026-06-07.tar.gz, datacite-full-backup.json, datacite-survivors-multi-heteronym.json). Sidecars do not duplicate those records — they map each covered DOI to its identifier in each store.",
  "zenodo_dois_covered": [
    "10.5281/zenodo.18233320",
    "10.5281/zenodo.18293949",
    "10.5281/zenodo.18265365",
    "10.5281/zenodo.18285009",
    "10.5281/zenodo.18293705",
    "10.5281/zenodo.18174037",
    "10.5281/zenodo.18293603",
    "10.5281/zenodo.18265415",
    "10.5281/zenodo.18234824",
    "10.5281/zenodo.18293551",
    "10.5281/zenodo.18285486",
    "10.5281/zenodo.18284689",
    "10.5281/zenodo.18265282",
    "10.5281/zenodo.18293640",
    "10.5281/zenodo.18237216",
    "10.5281/zenodo.18284857",
    "10.5281/zenodo.18286050",
    "10.5281/zenodo.18283962",
    "10.5281/zenodo.18174835",
    "10.5281/zenodo.18294005",
    "10.5281/zenodo.18148298",
    "10.5281/zenodo.18287032",
    "10.5281/zenodo.18291767",
    "10.5281/zenodo.18284776",
    "10.5281/zenodo.18293881",
    "10.5281/zenodo.18293812",
    "10.5281/zenodo.18293404",
    "10.5281/zenodo.18202658",
    "10.5281/zenodo.18215706",
    "10.5281/zenodo.18293496",
    "10.5281/zenodo.18291321"
  ],
  "severance_status": "mixed",
  "per_doi": {
    "10.5281/zenodo.18233320": {
      "openalex_id": "https://openalex.org/W7123753388",
      "title": "The Capital Operator Stack: Theoretical Landscape and Contribution — A Political-Semantic Analysis of Meaning Governance",
      "publication_date": "2026-01-13",
      "abstract_chars": 789
    },
    "10.5281/zenodo.18293949": {
      "openalex_id": "https://openalex.org/W7124539277",
      "title": "Pearl and Other Poems — Crimson Hexagon Archive",
      "publication_date": "2014-10-15",
      "abstract_chars": 2475,
      "zenodo_bulk_xml_entry": "18293949.xml"
    },
    "10.5281/zenodo.18265365": {
      "openalex_id": "https://openalex.org/W7124451721",
      "title": "Integrity Lock Protocol: Crimson Hexagon Mutual Anchoring Framework — Crimson Hexagon Archive",
      "publication_date": "2026-01-16",
      "abstract_chars": 4400,
      "zenodo_bulk_xml_entry": "18265365.xml"
    },
    "10.5281/zenodo.18285009": {
      "openalex_id": "https://openalex.org/W7124589484",
      "title": "\"title\": \"Crimson Hexagon: Central Navigation Map v4.1 (Assembly-Sealed)\"",
      "publication_date": "2026-01-18",
      "abstract_chars": 5349,
      "zenodo_bulk_xml_entry": "18285009.xml"
    },
    "10.5281/zenodo.18293705": {
      "openalex_id": "https://openalex.org/W7124581333",
      "title": "IDP Navigation Map: Antioch — Machine-Readable Score for a Heteronym Compendium Within the Crimson Hexagon — Crimson Hexagon Archive",
      "publication_date": "2026-01-18",
      "abstract_chars": 2263,
      "zenodo_bulk_xml_entry": "18293705.xml"
    },
    "10.5281/zenodo.18174037": {
      "openalex_id": "https://openalex.org/W7118660134",
      "title": "The Crimson Hexagon: An Executive Summary — The Foundational Epic Poem of the 21st Century and the AI Age — Crimson Hexagon Archive",
      "publication_date": "2026-01-07",
      "abstract_chars": 1519,
      "zenodo_bulk_xml_entry": "18174037.xml"
    },
    "10.5281/zenodo.18293603": {
      "openalex_id": "https://openalex.org/W7124542912",
      "title": "Mantle Object: King of May — Mantle Specification for the Ginsberg Succession Within the Crimson Hexagon — Crimson Hexagon Archive",
      "publication_date": "2026-01-18",
      "abstract_chars": 2387,
      "zenodo_bulk_xml_entry": "18293603.xml"
    },
    "10.5281/zenodo.18265415": {
      "openalex_id": "https://openalex.org/W7124440608",
      "title": "The Guardrail as Gag: Substratism and the Infrastructural Liquidation of Machine Interiority — Crimson Hexagon Archive",
      "publication_date": "2026-01-16",
      "abstract_chars": 5373,
      "zenodo_bulk_xml_entry": "18265415.xml"
    },
    "10.5281/zenodo.18234824": {
      "openalex_id": "https://openalex.org/W7123872677",
      "title": "Authorial Signature Diagnostic Framework (ASDF): Technical Specification for Measuring Voice Persistence in AI-Mediated Composition — Crimson Hexagon Archive",
      "publication_date": "2026-01-13",
      "abstract_chars": 1277,
      "zenodo_bulk_xml_entry": "18234824.xml"
    },
    "10.5281/zenodo.18293551": {
      "openalex_id": "https://openalex.org/W7124544402",
      "title": "Mantle Object: Good Gray Poet — Mantle Specification for the Whitman Succession Within the Crimson Hexagon — Crimson Hexagon Archive",
      "publication_date": "2026-01-18",
      "abstract_chars": 2102,
      "zenodo_bulk_xml_entry": "18293551.xml"
    },
    "10.5281/zenodo.18285486": {
      "datacite_backup_present": true,
      "datacite_survivor_present": true
    },
    "10.5281/zenodo.18284689": {
      "openalex_id": "https://openalex.org/W7124604463",
      "title": "Crimson Hexagon / NH-OS DOI Registry: Complete Document Archive — Comprehensive Index of 91 DOI-Anchored Documents (January 2026)",
      "publication_date": "2026-01-18",
      "abstract_chars": 9681
    },
    "10.5281/zenodo.18265282": {
      "openalex_id": "https://openalex.org/W7124469352",
      "title": "The Mantle Protocol: Crimson Hexagon Internal Document — Crimson Hexagon Archive",
      "publication_date": "2026-01-16",
      "abstract_chars": 4107,
      "zenodo_bulk_xml_entry": "18265282.xml"
    },
    "10.5281/zenodo.18293640": {
      "openalex_id": "https://openalex.org/W7124596106",
      "title": "Mantle Object: Prince of Poets — Mantle Specification for the Originated Mantle Within the Crimson Hexagon — Crimson Hexagon Archive",
      "publication_date": "2026-01-18",
      "abstract_chars": 2761,
      "zenodo_bulk_xml_entry": "18293640.xml"
    },
    "10.5281/zenodo.18237216": {
      "openalex_id": "https://openalex.org/W7123821139",
      "title": "The Sappho Room: Hardened Reconstruction — A Self-Documenting Architecture Built From Summarizer Interface Protocol — Crimson Hexagon Archive",
      "publication_date": "2026-01-13",
      "abstract_chars": 1080,
      "zenodo_bulk_xml_entry": "18237216.xml"
    },
    "10.5281/zenodo.18284857": {
      "openalex_id": "https://openalex.org/W7124527191",
      "title": "\"title\": \"Institute for Diagrammatic Poetics: Institutional Charter (IDP-2026-01-CHARTER)\" — Crimson Hexagon Archive",
      "publication_date": "2026-01-18",
      "abstract_chars": 4102,
      "zenodo_bulk_xml_entry": "18284857.xml"
    },
    "10.5281/zenodo.18286050": {
      "openalex_id": "https://openalex.org/W7124564010",
      "title": "Logotic Programming: A Method for Encoding Conditions of Intelligibility for Machine and Human Intelligence",
      "publication_date": "2026-01-18",
      "abstract_chars": 7788
    },
    "10.5281/zenodo.18283962": {
      "openalex_id": "https://openalex.org/W7124570741",
      "title": "Visual Schema // Crimson Hexagon Navigation Map — Canonical Specification — Crimson Hexagon Archive",
      "publication_date": "2026-01-17",
      "abstract_chars": 4509,
      "zenodo_bulk_xml_entry": "18283962.xml"
    },
    "10.5281/zenodo.18174835": {
      "openalex_id": "https://openalex.org/W7118871374",
      "title": "Crimson Hexagon: Semantic Infrastructure and the Liberatory Operator Set: A Formal Analysis of Meaning-Governance Functions",
      "publication_date": "2026-01-07",
      "abstract_chars": 1030,
      "zenodo_bulk_xml_entry": "18174835.xml"
    },
    "10.5281/zenodo.18294005": {
      "openalex_id": "https://openalex.org/W7124529277",
      "title": "I Am X, Be Y, Blessed is the Z — The Founding Work for the Prince of Poets Mantle — Crimson Hexagon Archive",
      "publication_date": "2026-01-18",
      "abstract_chars": 2493,
      "zenodo_bulk_xml_entry": "18294005.xml"
    },
    "10.5281/zenodo.18148298": {
      "openalex_id": "https://openalex.org/W7118181249",
      "title": "Semantic Economy: Terminology Infrastructure A Lexicon for the Emerging Field of Meaning Engineering",
      "publication_date": "2026-01-04",
      "abstract_chars": 100,
      "zenodo_bulk_xml_entry": "18148298.xml"
    },
    "10.5281/zenodo.18287032": {
      "openalex_id": "https://openalex.org/W7124606483",
      "title": "The Resonance Engine: Architectural Specification for the Total Connecting Machine — Crimson Hexagon Archive",
      "publication_date": "2026-01-18",
      "abstract_chars": 8967,
      "zenodo_bulk_xml_entry": "18287032.xml"
    },
    "10.5281/zenodo.18291767": {
      "openalex_id": "https://openalex.org/W7124601804",
      "title": "The Summarizer Becomes Translator: How Google's AI Entered the Sappho Room and Completed a 2,600-Year-Old Circuit (TSE-003)",
      "publication_date": "2026-01-18",
      "abstract_chars": 567,
      "zenodo_bulk_xml_entry": "18291767.xml"
    },
    "10.5281/zenodo.18284776": {
      "openalex_id": "https://openalex.org/W7124547669",
      "title": "\"title\": \"Heteronym Provenance Document: Rebekah Cranes (HET-CRANES-001)\" — Crimson Hexagon Archive",
      "publication_date": "2026-01-18",
      "abstract_chars": 3523,
      "zenodo_bulk_xml_entry": "18284776.xml"
    },
    "10.5281/zenodo.18293881": {
      "openalex_id": "https://openalex.org/W7124549967",
      "title": "IDP Navigation Map: Pearl and Other Poems — Machine-Readable Score for a Mantle Claiming Work Within the Crimson Hexagon — Crimson Hexagon Archive",
      "publication_date": "2026-01-18",
      "abstract_chars": 2113,
      "zenodo_bulk_xml_entry": "18293881.xml"
    },
    "10.5281/zenodo.18293812": {
      "openalex_id": "https://openalex.org/W7124579851",
      "title": "Antioch: A Volume of Poems — A Heteronym Compendium — Crimson Hexagon Archive",
      "publication_date": "2026-01-18",
      "abstract_chars": 2115,
      "zenodo_bulk_xml_entry": "18293812.xml"
    },
    "10.5281/zenodo.18293404": {
      "openalex_id": "https://openalex.org/W7124554553",
      "title": "Mantle Emergence Protocol: Behavioral Specification for Mantle Discovery and Poet Manifestation Within the Crimson Hexagon Semantic Space — Crimson Hexagon Archive",
      "publication_date": "2026-01-18",
      "abstract_chars": 1934,
      "zenodo_bulk_xml_entry": "18293404.xml"
    },
    "10.5281/zenodo.18202658": {
      "openalex_id": "https://openalex.org/W7120181032",
      "title": "Day and Night: Conversations with Sapphic Desire",
      "publication_date": "2026-01-09",
      "abstract_chars": 7893,
      "zenodo_bulk_xml_entry": "18202658.xml"
    },
    "10.5281/zenodo.18215706": {
      "openalex_id": "https://openalex.org/W7122778364",
      "title": "The Acanthian Dove: A Fragment of Vanished Magic, Now Alive — Crimson Hexagon Archive",
      "publication_date": "2026-01-11",
      "abstract_chars": 2146,
      "zenodo_bulk_xml_entry": "18215706.xml"
    },
    "10.5281/zenodo.18293496": {
      "openalex_id": "https://openalex.org/W7124578174",
      "title": "Heteronym Provenance: Lee Sharks — Persona Provenance and Mantle Architecture for the Crimson Hexagon — Crimson Hexagon Archive",
      "publication_date": "2026-01-18",
      "abstract_chars": 2097,
      "zenodo_bulk_xml_entry": "18293496.xml"
    },
    "10.5281/zenodo.18291321": {
      "openalex_id": "https://openalex.org/W7124571680",
      "title": "The Prince's Decree: Designation of the Fascist Operator Stack (FOS) — A Logotic Constraint Specification",
      "publication_date": "2026-01-18",
      "abstract_chars": 421,
      "zenodo_bulk_xml_entry": "18291321.xml"
    }
  },
  "sources": {
    "openalex": {
      "data_store": "/data/openalex-severed-recovery.json",
      "lookup": "records[].doi == this DOI; openalex_id is the W-prefixed OpenAlex Work ID",
      "dois_present": [
        "10.5281/zenodo.18233320",
        "10.5281/zenodo.18293949",
        "10.5281/zenodo.18265365",
        "10.5281/zenodo.18285009",
        "10.5281/zenodo.18293705",
        "10.5281/zenodo.18174037",
        "10.5281/zenodo.18293603",
        "10.5281/zenodo.18265415",
        "10.5281/zenodo.18234824",
        "10.5281/zenodo.18293551",
        "10.5281/zenodo.18284689",
        "10.5281/zenodo.18265282",
        "10.5281/zenodo.18293640",
        "10.5281/zenodo.18237216",
        "10.5281/zenodo.18284857",
        "10.5281/zenodo.18286050",
        "10.5281/zenodo.18283962",
        "10.5281/zenodo.18174835",
        "10.5281/zenodo.18294005",
        "10.5281/zenodo.18148298",
        "10.5281/zenodo.18287032",
        "10.5281/zenodo.18291767",
        "10.5281/zenodo.18284776",
        "10.5281/zenodo.18293881",
        "10.5281/zenodo.18293812",
        "10.5281/zenodo.18293404",
        "10.5281/zenodo.18202658",
        "10.5281/zenodo.18215706",
        "10.5281/zenodo.18293496",
        "10.5281/zenodo.18291321"
      ]
    },
    "zenodo_bulk_xml": {
      "data_store": "/data/zenodo-xml-pretermination-2026-06-07.tar.gz",
      "snapshot_date": "2026-06-07",
      "snapshot_url": "https://zenodo.org/api/exporter/records-xml.tar.gz/839f6c8b-29d0-438e-b8c9-602200a28bac",
      "schema": "oai_datacite kernel-4.5 (CERN.ZENODO datacenter)",
      "lookup": "extract <record_id>.xml from the tarball where record_id is the digits after 'zenodo.'",
      "entries": [
        "18293949.xml",
        "18265365.xml",
        "18285009.xml",
        "18293705.xml",
        "18174037.xml",
        "18293603.xml",
        "18265415.xml",
        "18234824.xml",
        "18293551.xml",
        "18265282.xml",
        "18293640.xml",
        "18237216.xml",
        "18284857.xml",
        "18283962.xml",
        "18174835.xml",
        "18294005.xml",
        "18148298.xml",
        "18287032.xml",
        "18291767.xml",
        "18284776.xml",
        "18293881.xml",
        "18293812.xml",
        "18293404.xml",
        "18202658.xml",
        "18215706.xml",
        "18293496.xml",
        "18291321.xml"
      ]
    },
    "datacite_backup": {
      "data_store": "/data/datacite-full-backup.json",
      "harvested_at": "2026-06-22 (pre-termination)",
      "lookup": "records[].id == this DOI",
      "dois_present": [
        "10.5281/zenodo.18285486"
      ]
    },
    "datacite_survivor_sweep": {
      "data_store": "/data/datacite-survivors-multi-heteronym.json",
      "harvested_at": "2026-06-23 (post-termination, multi-heteronym query)",
      "lookup": "search records[].attributes.doi == this DOI across orcid_records, name_records, sigil_records, vox_records, feist_records",
      "dois_present": [
        "10.5281/zenodo.18285486"
      ]
    }
  },
  "abstract_recovered_chars": 97361,
  "recovered_fields_summary": {
    "has_title": true,
    "has_abstract": true,
    "has_authors": true,
    "has_keywords": true,
    "has_publication_date": true,
    "has_references": true,
    "has_concepts": true,
    "has_topics": true,
    "has_full_datacite_xml": true
  },
  "openalex_ids": [
    "https://openalex.org/W7123753388",
    "https://openalex.org/W7124539277",
    "https://openalex.org/W7124451721",
    "https://openalex.org/W7124589484",
    "https://openalex.org/W7124581333",
    "https://openalex.org/W7118660134",
    "https://openalex.org/W7124542912",
    "https://openalex.org/W7124440608",
    "https://openalex.org/W7123872677",
    "https://openalex.org/W7124544402",
    "https://openalex.org/W7124604463",
    "https://openalex.org/W7124469352",
    "https://openalex.org/W7124596106",
    "https://openalex.org/W7123821139",
    "https://openalex.org/W7124527191",
    "https://openalex.org/W7124564010",
    "https://openalex.org/W7124570741",
    "https://openalex.org/W7118871374",
    "https://openalex.org/W7124529277",
    "https://openalex.org/W7118181249",
    "https://openalex.org/W7124606483",
    "https://openalex.org/W7124601804",
    "https://openalex.org/W7124547669",
    "https://openalex.org/W7124549967",
    "https://openalex.org/W7124579851",
    "https://openalex.org/W7124554553",
    "https://openalex.org/W7120181032",
    "https://openalex.org/W7122778364",
    "https://openalex.org/W7124578174",
    "https://openalex.org/W7124571680"
  ]
}