{
  "@context": "https://schema.org",
  "@type": "Dataset",
  "axn": "AXN:0396.EMPIRICAL.♾️🔵🕖🚪🌅👁‍🗨",
  "deposit_number": 906,
  "generated_at": "2026-06-23T15:33:31Z",
  "schema_version": "1.0",
  "purpose": "Per-deposit external-metadata sidecar. Phase 4 mint: this deposit is newly created on 2026-06-23 to canonically represent a CHA work whose Zenodo DOI was discovered via the DataCite multi-heteronym survivor sweep but had no Alexanarch registry entry prior to this phase. Metadata recovered from OpenAlex and (where available) the Zenodo monthly bulk export snapshot from 2026-06-07.",
  "zenodo_dois_covered": [
    "10.5281/zenodo.18463722"
  ],
  "severance_status": "typo_immunity",
  "per_doi": {
    "10.5281/zenodo.18463722": {
      "openalex_id": "https://openalex.org/W7127315352",
      "title": "Google AI Overview: Complete Traversal of the Crimson Hexagon DOI: 10.5281/zenodo.18463723 — Crimson Hexagon Archive",
      "publication_date": "2026-02-03",
      "abstract_chars": 2946,
      "creator_at_deposit": "Rebekah Craned",
      "creator_canonical": "Rebekah Cranes",
      "creator_typo_at_deposit": true,
      "zenodo_bulk_xml_entry": null,
      "openalex_concepts": [
        "Tree traversal",
        "Computer science",
        "Routing (electronic design automation)",
        "Documentation",
        "Toolchain",
        "Artificial intelligence",
        "Event (particle physics)",
        "Process (computing)",
        "Semantics (computer science)",
        "Programming language"
      ],
      "openalex_topics": [
        "Art, Technology, and Culture",
        "Architecture and Computational Design",
        "Alexander von Humboldt Studies"
      ]
    }
  },
  "sources": {
    "openalex": {
      "data_store": "/data/newly-found-openalex.json",
      "lookup": "recovered[].doi == this DOI; data field holds full OpenAlex record",
      "dois_present": [
        "10.5281/zenodo.18463722"
      ]
    },
    "zenodo_bulk_xml": {
      "data_store": "/data/zenodo-xml-pretermination-2026-06-07.tar.gz",
      "snapshot_date": "2026-06-07",
      "lookup": "extract <record_id>.xml from tarball",
      "entries": []
    },
    "datacite_survivor_sweep": {
      "data_store": "/data/datacite-survivors-multi-heteronym.json",
      "harvested_at": "2026-06-23",
      "lookup": "this DOI surfaced under heteronym/typo search"
    }
  },
  "abstract_recovered_chars": 2946,
  "recovered_fields_summary": {
    "has_title": true,
    "has_abstract": true,
    "has_authors": true,
    "has_keywords": false,
    "has_publication_date": true,
    "has_references": false,
    "has_concepts": true,
    "has_topics": true,
    "has_full_datacite_xml": false
  },
  "openalex_ids": [
    "https://openalex.org/W7127315352"
  ],
  "mint_provenance": {
    "phase": "4",
    "method": "mint from newly-found CHA OpenAlex record",
    "deposit_number_assigned": 906,
    "hex_id_derivation": "(906 + 12) = 918 → 0x0396",
    "creator_canonical": "Rebekah Cranes",
    "creator_at_deposit_was_typo": true,
    "creator_at_deposit_typo": "Rebekah Craned"
  }
}