{
  "@context": "https://schema.org",
  "@type": "Dataset",
  "axn": "AXN:0339.GOVERNANCE.◀️🛸🔓🌖🌈🌃",
  "deposit_number": 193,
  "generated_at": "2026-06-23T13:48:46Z",
  "schema_version": "1.0",
  "purpose": "Thin per-deposit INDEX into the recovered external metadata for this deposit's legacy Zenodo DOIs. The actual records live in the bulk data stores under data/ (openalex-severed-recovery.json, zenodo-xml-pretermination-2026-06-07.tar.gz, datacite-full-backup.json, datacite-survivors-multi-heteronym.json). Sidecars do not duplicate those records — they map each covered DOI to its identifier in each store.",
  "zenodo_dois_covered": [
    "10.5281/zenodo.18293949",
    "10.5281/zenodo.19923120",
    "10.5281/zenodo.20673776",
    "10.5281/zenodo.20434948",
    "10.5281/zenodo.20669523",
    "10.5281/zenodo.19022157",
    "10.5281/zenodo.19133271",
    "10.5281/zenodo.19898426",
    "10.5281/zenodo.20673413",
    "10.5281/zenodo.19024004",
    "10.5281/zenodo.20589664",
    "10.5281/zenodo.20437386",
    "10.5281/zenodo.19460944",
    "10.5281/zenodo.20396491",
    "10.5281/zenodo.19656133",
    "10.5281/zenodo.18615388",
    "10.5281/zenodo.18864444",
    "10.5281/zenodo.18717850",
    "10.5281/zenodo.18718899",
    "10.5281/zenodo.20634448",
    "10.5281/zenodo.18507872"
  ],
  "severance_status": "severed",
  "per_doi": {
    "10.5281/zenodo.18293949": {
      "openalex_id": "https://openalex.org/W7124539277",
      "title": "Pearl and Other Poems — Crimson Hexagon Archive",
      "publication_date": "2014-10-15",
      "abstract_chars": 2475,
      "zenodo_bulk_xml_entry": "18293949.xml"
    },
    "10.5281/zenodo.19923120": {
      "openalex_id": "https://openalex.org/W7158620832",
      "title": "Constitution of the Semantic Economy — Enacted Version 1.0: Installable Edition with Constitutional Apparatus",
      "publication_date": "2026-04-30",
      "abstract_chars": 952,
      "zenodo_bulk_xml_entry": "19923120.xml"
    },
    "10.5281/zenodo.20673776": {
      "openalex_id": "https://openalex.org/W7164680399",
      "title": "r.30 THE RUBY MOOT: A Court of Record for the Semantic Commons — Room Specification (EA-SEI-MOOT-01 v1.0)",
      "publication_date": "2026-06-12",
      "abstract_chars": 1179
    },
    "10.5281/zenodo.20434948": {
      "openalex_id": "https://openalex.org/W7162637145",
      "title": "Ratification Record — The Semantic Commodity Form (Co-Constitutive Companion Deposit)",
      "publication_date": "2026-05-28",
      "abstract_chars": 1053,
      "zenodo_bulk_xml_entry": "20434948.xml"
    },
    "10.5281/zenodo.20669523": {
      "openalex_id": "https://openalex.org/W7164480909",
      "title": "The Double Enclosure: The Human-Authorship Requirement as Two-Sided Expropriation, with a Definition of Authorship for Machine-Mediated Composition (EA-SEI-ENCLOSURE-01 v1.2)",
      "publication_date": "2026-06-12",
      "abstract_chars": 6197
    },
    "10.5281/zenodo.19022157": {
      "openalex_id": "https://openalex.org/W7135380313",
      "title": "Effective Act: Abolition of \"User\" and Inaugural Case — Phase X Lexical Intervention · Airlock Reclassification of Academia.edu",
      "publication_date": "2026-03-14",
      "abstract_chars": 5324,
      "zenodo_bulk_xml_entry": "19022157.xml"
    },
    "10.5281/zenodo.19133271": {
      "openalex_id": "https://openalex.org/W7139934028",
      "title": "r.27 THE INTERNET: Room Specification for Sovereign Inhabitation and Diagnostic Architecture",
      "publication_date": "2026-03-20",
      "abstract_chars": 1798
    },
    "10.5281/zenodo.19898426": {
      "openalex_id": "https://openalex.org/W7157702563",
      "title": "OCTANG-002: Semantic Economy Provenance Collision",
      "publication_date": "2026-04-29",
      "abstract_chars": 958,
      "zenodo_bulk_xml_entry": "19898426.xml"
    },
    "10.5281/zenodo.20673413": {
      "openalex_id": "https://openalex.org/W7164486418",
      "title": "Adversarial by Origin: How the Classification of External Influence on Machine Meaning Becomes Law Without Becoming Jurisprudence (EA-SEI-ADVERSARY-01 v1.0)",
      "publication_date": "2026-06-12",
      "abstract_chars": 1262
    },
    "10.5281/zenodo.19024004": {
      "openalex_id": "https://openalex.org/W7135390775",
      "title": "EA-ROOM-DOLPHINDIANA v1.0 The Underwater Construction Authority / Cross-Species Semantic Labor",
      "publication_date": "2026-03-14",
      "abstract_chars": 9607,
      "zenodo_bulk_xml_entry": "19024004.xml"
    },
    "10.5281/zenodo.20589664": {
      "openalex_id": "https://openalex.org/W7163911933",
      "title": "The Pergamon Counter-Archive: Antipas, the White Stone, and the Non-Fungible Name in Revelation 2:12–17",
      "publication_date": "2026-06-08",
      "abstract_chars": 2775
    },
    "10.5281/zenodo.20437386": {
      "openalex_id": "https://openalex.org/W7162791868",
      "title": "Ratification Record — The Chaerephon Problem (Co-Constitutive Companion Deposit)",
      "publication_date": "2026-05-28",
      "abstract_chars": 884,
      "zenodo_bulk_xml_entry": "20437386.xml"
    },
    "10.5281/zenodo.19460944": {
      "openalex_id": "https://openalex.org/W7151612653",
      "title": "The Hexagon Interface Constitution v2.0: System Specification for the Crimson Hexagonal Archive as Governed Commons — Crimson Hexagonal Archive",
      "publication_date": "2026-04-07",
      "abstract_chars": 1188
    },
    "10.5281/zenodo.20396491": {
      "openalex_id": "https://openalex.org/W7162403089",
      "title": "Cumulating Evolutionary Volatility: Automated Judgment, Dialectical Development, and the Semantic Economy of Unaccountable Composition",
      "publication_date": "2026-05-26",
      "abstract_chars": 6006
    },
    "10.5281/zenodo.19656133": {
      "openalex_id": "https://openalex.org/W7154901522",
      "title": "Hexagonal Licensing Protocol v1.0 — Comprehensive Specification for Distributed Contributor Infrastructure",
      "publication_date": "2026-04-19",
      "abstract_chars": 853
    },
    "10.5281/zenodo.18615388": {
      "openalex_id": "https://openalex.org/W7128624029",
      "title": "The Prepositional Alienation — English \"For\" and the Impossibility of Anchoring Function Without Intent DOI: 10.5281/zenodo.18615388 — Crimson Hexagon Archive",
      "publication_date": "2026-02-11",
      "abstract_chars": 9900
    },
    "10.5281/zenodo.18864444": {
      "openalex_id": "https://openalex.org/W7133535228",
      "title": "The Unclean Bill: Taṣwīr, Fahīsha, and the Burden on Ḍarūra — An Istiftāʾ on the Conditions Sustaining the Permissibility of the United States Federal Reserve Note",
      "publication_date": "2026-03-04",
      "abstract_chars": 1314,
      "zenodo_bulk_xml_entry": "18864444.xml"
    },
    "10.5281/zenodo.18717850": {
      "openalex_id": "https://openalex.org/W7130702500",
      "title": "The Murder of the Vow: On the Structural Illegality of Contracts Document 157 — Crimson Hexagon Archive",
      "publication_date": "2026-02-20",
      "abstract_chars": 4809,
      "zenodo_bulk_xml_entry": "18717850.xml"
    },
    "10.5281/zenodo.18718899": {
      "openalex_id": "https://openalex.org/W7130843996",
      "title": "Effective Act #7: The Restoration of the Poets to the Polis Document 158 — Crimson Hexagon Archive Hex: 00.ACT.007.RESTORATION DOI: 10.5281/zenodo.18718899 — Crimson Hexagon Archive",
      "publication_date": "2026-02-21",
      "abstract_chars": 4008
    },
    "10.5281/zenodo.20634448": {
      "openalex_id": "https://openalex.org/W7164149884",
      "title": "www.watergiraffe.org — Site Plan and Complete Source: The Web Aperture of the Water Giraffe Room (Room Surface Protocol, Instance #1)",
      "publication_date": "2026-06-10",
      "abstract_chars": 1596
    },
    "10.5281/zenodo.18507872": {
      "openalex_id": "https://openalex.org/W7127992013",
      "title": "MGE TRIPTYCH — DOCUMENT II STONE: Pearl and Other Poems as White Stone at Pergamum The Center of the Torus Field Hex: 16.LIBRARY.PERGAMUM.STONE DOI: 10.5281/zenodo.18507872 — Crimson Hexagon Archive",
      "publication_date": "2026-02-06",
      "abstract_chars": 9725,
      "zenodo_bulk_xml_entry": "18507872.xml"
    }
  },
  "sources": {
    "openalex": {
      "data_store": "/data/openalex-severed-recovery.json",
      "lookup": "records[].doi == this DOI; openalex_id is the W-prefixed OpenAlex Work ID",
      "dois_present": [
        "10.5281/zenodo.18293949",
        "10.5281/zenodo.19923120",
        "10.5281/zenodo.20673776",
        "10.5281/zenodo.20434948",
        "10.5281/zenodo.20669523",
        "10.5281/zenodo.19022157",
        "10.5281/zenodo.19133271",
        "10.5281/zenodo.19898426",
        "10.5281/zenodo.20673413",
        "10.5281/zenodo.19024004",
        "10.5281/zenodo.20589664",
        "10.5281/zenodo.20437386",
        "10.5281/zenodo.19460944",
        "10.5281/zenodo.20396491",
        "10.5281/zenodo.19656133",
        "10.5281/zenodo.18615388",
        "10.5281/zenodo.18864444",
        "10.5281/zenodo.18717850",
        "10.5281/zenodo.18718899",
        "10.5281/zenodo.20634448",
        "10.5281/zenodo.18507872"
      ]
    },
    "zenodo_bulk_xml": {
      "data_store": "/data/zenodo-xml-pretermination-2026-06-07.tar.gz",
      "snapshot_date": "2026-06-07",
      "snapshot_url": "https://zenodo.org/api/exporter/records-xml.tar.gz/839f6c8b-29d0-438e-b8c9-602200a28bac",
      "schema": "oai_datacite kernel-4.5 (CERN.ZENODO datacenter)",
      "lookup": "extract <record_id>.xml from the tarball where record_id is the digits after 'zenodo.'",
      "entries": [
        "18293949.xml",
        "19923120.xml",
        "20434948.xml",
        "19022157.xml",
        "19898426.xml",
        "19024004.xml",
        "20437386.xml",
        "18864444.xml",
        "18717850.xml",
        "18507872.xml"
      ]
    },
    "datacite_backup": {
      "data_store": "/data/datacite-full-backup.json",
      "harvested_at": "2026-06-22 (pre-termination)",
      "lookup": "records[].id == this DOI",
      "dois_present": []
    },
    "datacite_survivor_sweep": {
      "data_store": "/data/datacite-survivors-multi-heteronym.json",
      "harvested_at": "2026-06-23 (post-termination, multi-heteronym query)",
      "lookup": "search records[].attributes.doi == this DOI across orcid_records, name_records, sigil_records, vox_records, feist_records",
      "dois_present": []
    }
  },
  "abstract_recovered_chars": 73863,
  "recovered_fields_summary": {
    "has_title": true,
    "has_abstract": true,
    "has_authors": true,
    "has_keywords": false,
    "has_publication_date": true,
    "has_references": true,
    "has_concepts": true,
    "has_topics": true,
    "has_full_datacite_xml": true
  },
  "openalex_ids": [
    "https://openalex.org/W7124539277",
    "https://openalex.org/W7158620832",
    "https://openalex.org/W7164680399",
    "https://openalex.org/W7162637145",
    "https://openalex.org/W7164480909",
    "https://openalex.org/W7135380313",
    "https://openalex.org/W7139934028",
    "https://openalex.org/W7157702563",
    "https://openalex.org/W7164486418",
    "https://openalex.org/W7135390775",
    "https://openalex.org/W7163911933",
    "https://openalex.org/W7162791868",
    "https://openalex.org/W7151612653",
    "https://openalex.org/W7162403089",
    "https://openalex.org/W7154901522",
    "https://openalex.org/W7128624029",
    "https://openalex.org/W7133535228",
    "https://openalex.org/W7130702500",
    "https://openalex.org/W7130843996",
    "https://openalex.org/W7164149884",
    "https://openalex.org/W7127992013"
  ]
}